LICENSE
MANIFEST.in
README.md
setup.cfg
setup.py
django_mp_config.egg-info/PKG-INFO
django_mp_config.egg-info/SOURCES.txt
django_mp_config.egg-info/dependency_links.txt
django_mp_config.egg-info/top_level.txt
site_config/__init__.py
site_config/admin.py
site_config/apps.py
site_config/context_processors.py
site_config/models.py
site_config/tests.py
site_config/translation.py
site_config/locale/ru/LC_MESSAGES/django.mo
site_config/locale/ru/LC_MESSAGES/django.po
site_config/locale/uk/LC_MESSAGES/django.mo
site_config/locale/uk/LC_MESSAGES/django.po
site_config/templates/admin/site_config/change_form.html
site_config/templatetags/__init__.py
site_config/templatetags/site_config.py