Metadata-Version: 2.1
Name: django-mp-config
Version: 6.0.0
Summary: Django site settings app
Home-page: https://github.com/pmaigutyak/mp-config
Author: Paul Maigutyak
Author-email: pmaigutyak@gmail.com
License: MIT
Download-URL: https://github.com/pmaigutyak/mp-config/archive/6.0.0.tar.gz
Platform: UNKNOWN
License-File: LICENSE
